flask_htmlmin/__init__.py
Flask_HTMLmin-3.0.0.dist-info/LICENSE
Flask_HTMLmin-3.0.0.dist-info/METADATA
Flask_HTMLmin-3.0.0.dist-info/WHEEL
Flask_HTMLmin-3.0.0.dist-info/top_level.txt
Flask_HTMLmin-3.0.0.dist-info/RECORD
