Metadata-Version: 2.1
Name: Flask-HTMLmin
Version: 3.0.0
Summary: Minify flask text/html mime type responses
Home-page: https://github.com/hamidfzm/Flask-HTMLmin
Author: Hamid FzM
Author-email: hamidfzm@gmail.com
License: BSD-3-Clause
Platform: any
Classifier: Environment :: Web Environment
Classifier: Intended Audience :: Developers
Classifier: License :: OSI Approved :: BSD License
Classifier: Operating System :: OS Independent
Classifier: Programming Language :: Python
Classifier: Programming Language :: Python :: 3.8
Classifier: Programming Language :: Python :: 3.9
Classifier: Programming Language :: Python :: 3.10
Classifier: Programming Language :: Python :: 3.11
Classifier: Topic :: Internet :: WWW/HTTP :: Dynamic Content
Classifier: Topic :: Software Development :: Libraries :: Python Modules
Classifier: Topic :: Text Processing :: Markup :: HTML
Requires-Python: >=3.6
License-File: LICENSE
Requires-Dist: Flask
Requires-Dist: htmlmin2
Requires-Dist: cssmin
